poja/__init__.py
poja/__main__.py
poja/core.py
poja/version.py
poja/database/__init__.py
poja/genclients/__init__.py
poja/mygit/__init__.py
poja/myos/__init__.py
poja/myrich/__init__.py
poja/sed/__init__.py
poja/sentry/__init__.py
poja/sonar/__init__.py
poja/vpcscoped/__init__.py
poja-12.4.2.dist-info/LICENSE
poja-12.4.2.dist-info/METADATA
poja-12.4.2.dist-info/WHEEL
poja-12.4.2.dist-info/top_level.txt
poja-12.4.2.dist-info/RECORD
