Metadata-Version: 2.1
Name: poja
Version: 12.4.2
Summary: Serverless Postgres+Java hosted on Github+AWS
Home-page: https://github.com/hei-school/poja-cli
Author: HEI
Author-email: contact@hei.school
License: MIT
License-File: LICENSE
Requires-Dist: pyyaml
Requires-Dist: fire
Requires-Dist: gitpython
Requires-Dist: rich
